{
  "PropertySetDef": {
    "xmlns:xsd": "http://www.w3.org/2001/XMLSchema",
    "xmlns:xsi": "http://www.w3.org/2001/XMLSchema-instance",
    "ifdguid": "d213f780d1e711e1800000215ad4efdf",
    "templatetype": "PSET_TYPEDRIVENOVERRIDE",
    "xsi:noNamespaceSchemaLocation": "http://buildingSMART-tech.org/xml/psd/PSD_IFC4.xsd",
    "IfcVersion": {
      "version": "IFC4"
    },
    "Name": "Pset_FlowInstrumentTypeThermometer",
    "Definition": "A device that reads and displays a temperature value at a point.",
    "Applicability": null,
    "ApplicableClasses": {
      "ClassName": "IfcFlowInstrument/THERMOMETER"
    },
    "ApplicableTypeValue": "IfcFlowInstrument/THERMOMETER",
    "PropertyDefs": {
      "PropertyDef": [
        {
          "ifdguid": "d7714200d1e711e1800000215ad4efdf",
          "Name": "ThermometerType",
          "Definition": "Identifies the means by which temperature is displayed.",
          "PropertyType": {
            "TypePropertyEnumeratedValue": {
              "EnumList": {
                "name": "PEnum_ThermometerType",
                "EnumItem": [
                  "DIAL",
                  "DIGITAL",
                  "STEM",
                  "OTHER",
                  "NOTKNOWN",
                  "UNSET"
                ]
              },
              "ConstantList": {
                "ConstantDef": [
                  {
                    "Name": "DIAL",
                    "NameAliases": {
                      "NameAlias": {
                        "lang": "en",
                        "#text": "Dial"
                      }
                    },
                    "DefinitionAliases": {
                      "DefinitionAlias": {
                        "lang": "en"
                      }
                    }
                  },
                  {
                    "Name": "DIGITAL",
                    "NameAliases": {
                      "NameAlias": {
                        "lang": "en",
                        "#text": "Digital"
                      }
                    },
                    "DefinitionAliases": {
                      "DefinitionAlias": {
                        "lang": "en"
                      }
                    }
                  },
                  {
                    "Name": "STEM",
                    "NameAliases": {
                      "NameAlias": {
                        "lang": "en",
                        "#text": "Stem"
                      }
                    },
                    "DefinitionAliases": {
                      "DefinitionAlias": {
                        "lang": "en"
                      }
                    }
                  },
                  {
                    "Name": "OTHER",
                    "NameAliases": {
                      "NameAlias": {
                        "lang": "en",
                        "#text": "(other)"
                      }
                    },
                    "DefinitionAliases": {
                      "DefinitionAlias": {
                        "lang": "en",
                        "#text": "Value is not listed."
                      }
                    }
                  },
                  {
                    "Name": "NOTKNOWN",
                    "NameAliases": {
                      "NameAlias": {
                        "lang": "en",
                        "#text": "(unknown)"
                      }
                    },
                    "DefinitionAliases": {
                      "DefinitionAlias": {
                        "lang": "en",
                        "#text": "Value is unknown."
                      }
                    }
                  },
                  {
                    "Name": "UNSET",
                    "NameAliases": {
                      "NameAlias": {
                        "lang": "en",
                        "#text": "(unset)"
                      }
                    },
                    "DefinitionAliases": {
                      "DefinitionAlias": {
                        "lang": "en",
                        "#text": "Value has not been specified."
                      }
                    }
                  }
                ]
              }
            }
          }
        },
        {
          "ifdguid": "e5bf5e00d1e711e1800000215ad4efdf",
          "Name": "DisplaySize",
          "Definition": "The physical size of the display. In the case of a stem thermometer, this will be the length of the stem. For a dial thermometer, it will be the diameter of the dial.",
          "PropertyType": {
            "TypePropertySingleValue": {
              "DataType": {
                "type": "IfcPositiveLengthMeasure"
              }
            }
          }
        }
      ]
    }
  }
}