{
  "PropertySetDef": {
    "xmlns:xsd": "http://www.w3.org/2001/XMLSchema",
    "xmlns:xsi": "http://www.w3.org/2001/XMLSchema-instance",
    "ifdguid": "9e2dd780d1d111e1800000215ad4efdf",
    "templatetype": "PSET_TYPEDRIVENOVERRIDE",
    "xsi:noNamespaceSchemaLocation": "http://buildingSMART-tech.org/xml/psd/PSD_IFC4.xsd",
    "IfcVersion": {
      "version": "IFC4"
    },
    "Name": "Pset_DamperTypeControlDamper",
    "Definition": "Control damper type attributes.\nPset renamed from Pset_DamperTypeControl to Pset_DamperTypeControlDamper in IFC2x2 Pset Addendum.",
    "Applicability": null,
    "ApplicableClasses": {
      "ClassName": "IfcDamper/CONTROLDAMPER"
    },
    "ApplicableTypeValue": "IfcDamper/CONTROLDAMPER",
    "PropertyDefs": {
      "PropertyDef": [
        {
          "ifdguid": "a38b2200d1d111e1800000215ad4efdf",
          "Name": "TorqueRange",
          "Definition": "Torque range: minimum operational torque to maximum allowable torque.",
          "PropertyType": {
            "TypePropertyBoundedValue": {
              "DataType": {
                "type": "IfcTorqueMeasure"
              }
            }
          }
        },
        {
          "ifdguid": "aa199980d1d111e1800000215ad4efdf",
          "Name": "ControlDamperOperation",
          "Definition": "The inherent characteristic of the control damper operation.",
          "PropertyType": {
            "TypePropertyEnumeratedValue": {
              "EnumList": {
                "name": "PEnum_ControlDamperOperation",
                "EnumItem": [
                  "LINEAR",
                  "EXPONENTIAL",
                  "OTHER",
                  "NOTKNOWN",
                  "UNSET"
                ]
              },
              "ConstantList": {
                "ConstantDef": [
                  {
                    "Name": "LINEAR",
                    "NameAliases": {
                      "NameAlias": {
                        "lang": "en",
                        "#text": "Linear"
                      }
                    },
                    "DefinitionAliases": {
                      "DefinitionAlias": {
                        "lang": "en"
                      }
                    }
                  },
                  {
                    "Name": "EXPONENTIAL",
                    "NameAliases": {
                      "NameAlias": {
                        "lang": "en",
                        "#text": "Exponential"
                      }
                    },
                    "DefinitionAliases": {
                      "DefinitionAlias": {
                        "lang": "en"
                      }
                    }
                  },
                  {
                    "Name": "OTHER",
                    "NameAliases": {
                      "NameAlias": {
                        "lang": "en",
                        "#text": "(other)"
                      }
                    },
                    "DefinitionAliases": {
                      "DefinitionAlias": {
                        "lang": "en",
                        "#text": "Value is not listed."
                      }
                    }
                  },
                  {
                    "Name": "NOTKNOWN",
                    "NameAliases": {
                      "NameAlias": {
                        "lang": "en",
                        "#text": "(unknown)"
                      }
                    },
                    "DefinitionAliases": {
                      "DefinitionAlias": {
                        "lang": "en",
                        "#text": "Value is unknown."
                      }
                    }
                  },
                  {
                    "Name": "UNSET",
                    "NameAliases": {
                      "NameAlias": {
                        "lang": "en",
                        "#text": "(unset)"
                      }
                    },
                    "DefinitionAliases": {
                      "DefinitionAlias": {
                        "lang": "en",
                        "#text": "Value has not been specified."
                      }
                    }
                  }
                ]
              }
            }
          }
        }
      ]
    }
  }
}